deepview/modelpack/utils/argmax.py
edgefirst/validator/__init__.py
edgefirst/validator/__main__.py
edgefirst/validator/validate.py
edgefirst/validator/datasets/__init__.py
edgefirst/validator/datasets/cache.py
edgefirst/validator/datasets/core.py
edgefirst/validator/datasets/darknet.py
edgefirst/validator/datasets/database.py
edgefirst/validator/datasets/instance/__init__.py
edgefirst/validator/datasets/instance/core.py
edgefirst/validator/datasets/instance/detection.py
edgefirst/validator/datasets/instance/multitask.py
edgefirst/validator/datasets/instance/segmentation.py
edgefirst/validator/datasets/utils/annotation_transforms.py
edgefirst/validator/datasets/utils/fetch.py
edgefirst/validator/datasets/utils/image_transforms.py
edgefirst/validator/datasets/utils/readers.py
edgefirst/validator/evaluators/__init__.py
edgefirst/validator/evaluators/core.py
edgefirst/validator/evaluators/detection.py
edgefirst/validator/evaluators/multitask.py
edgefirst/validator/evaluators/segmentation.py
edgefirst/validator/evaluators/callbacks/__init__.py
edgefirst/validator/evaluators/callbacks/core.py
edgefirst/validator/evaluators/callbacks/plots.py
edgefirst/validator/evaluators/callbacks/stages.py
edgefirst/validator/evaluators/callbacks/studio.py
edgefirst/validator/evaluators/parameters/__init__.py
edgefirst/validator/evaluators/parameters/core.py
edgefirst/validator/evaluators/parameters/dataset.py
edgefirst/validator/evaluators/parameters/model.py
edgefirst/validator/evaluators/parameters/validation.py
edgefirst/validator/evaluators/utils/__init__.py
edgefirst/validator/evaluators/utils/classify.py
edgefirst/validator/evaluators/utils/match.py
edgefirst/validator/evaluators/utils/timer.py
edgefirst/validator/metrics/__init__.py
edgefirst/validator/metrics/detection.py
edgefirst/validator/metrics/segmentation.py
edgefirst/validator/metrics/data/__init__.py
edgefirst/validator/metrics/data/label.py
edgefirst/validator/metrics/data/metrics.py
edgefirst_validator-5.1.0.dist-info/METADATA
edgefirst_validator-5.1.0.dist-info/WHEEL
edgefirst_validator-5.1.0.dist-info/entry_points.txt
edgefirst_validator-5.1.0.dist-info/top_level.txt
edgefirst_validator-5.1.0.dist-info/RECORD
