Metadata-Version: 2.4
Name: edgefirst-validator
Version: 5.1.0
Summary: EdgeFirst Validator
Requires-Python: >=3.8
Requires-Dist: tqdm
Requires-Dist: Pillow
Requires-Dist: PyYAML
Requires-Dist: matplotlib
Requires-Dist: requests
Requires-Dist: numpy
Requires-Dist: lmdb
Requires-Dist: polars
Requires-Dist: edgefirst-client
Provides-Extra: keras
Requires-Dist: tensorflow[and-cuda]; extra == "keras"
Provides-Extra: onnx
Requires-Dist: onnxruntime-gpu; extra == "onnx"
Provides-Extra: tensorrt
Requires-Dist: tensorrt; extra == "tensorrt"
Requires-Dist: pycuda; extra == "tensorrt"
Provides-Extra: tflite
Requires-Dist: tflite_runtime; extra == "tflite"
Provides-Extra: studio
Requires-Dist: tensorflow[and-cuda]; extra == "studio"
Requires-Dist: onnxruntime-gpu; extra == "studio"
Requires-Dist: torch; extra == "studio"
Requires-Dist: torchvision; extra == "studio"
Requires-Dist: opencv-python-headless; extra == "studio"
